_pyexit.c
setup.py
PyExit.egg-info/PKG-INFO
PyExit.egg-info/SOURCES.txt
PyExit.egg-info/dependency_links.txt
PyExit.egg-info/top_level.txt
pyexit/__init__.py