Metadata-Version: 1.0
Name: PyExit
Version: 1.0.0
Summary: Exit the program
Home-page: UNKNOWN
Author: Vadim from PFTPrograms
Author-email: pftprograms@yandex.ru
License: UNKNOWN
Platform: UNKNOWN
